songfinder/__init__.py
songfinder/__main__.py
songfinder/accords.py
songfinder/background.py
songfinder/cache.py
songfinder/classDiapo.py
songfinder/classPaths.py
songfinder/classSet.py
songfinder/classSettings.py
songfinder/classVersets.py
songfinder/commandLine.py
songfinder/corrector.py
songfinder/dataAccords.py
songfinder/dataBase.py
songfinder/diapoList.py
songfinder/diapoPreview.py
songfinder/distances.py
songfinder/distances.pyx
songfinder/exception.py
songfinder/fileConverter.py
songfinder/fonctions.py
songfinder/gestchant.py
songfinder/latex.py
songfinder/libLoader.py
songfinder/logger_formatter.py
songfinder/messages.py
songfinder/pyreplace.py
songfinder/search.py
songfinder/setup_cython.py
songfinder/versionning.py
songfinder/data/icon.ico
songfinder/data/icon.png
songfinder/data/backgrounds/fond_bleu.jpg
songfinder/data/backgrounds/fond_noir.jpg
songfinder/data/htmlTemplates/defaultStyle.html
songfinder/data/latexTemplates/commandesImages.tex
songfinder/data/latexTemplates/entete.tex
songfinder/data/latexTemplates/enteteBeamer.tex
songfinder/data/latexTemplates/genBeamer.tex
songfinder/data/latexTemplates/genCarnet.tex
songfinder/data/latexTemplates/pageDeGarde.tex
songfinder/data/latexTemplates/tabulation.tex
songfinder/elements/__init__.py
songfinder/elements/cdlparser.py
songfinder/elements/chant.py
songfinder/elements/elements.py
songfinder/elements/exports.py
songfinder/elements/imageObj.py
songfinder/elements/passage.py
songfinder/gui/__init__.py
songfinder/gui/diapoListGui.py
songfinder/gui/editGui.py
songfinder/gui/fullScreenPresent.py
songfinder/gui/guiHelper.py
songfinder/gui/inputFrame.py
songfinder/gui/interface.py
songfinder/gui/preferences.py
songfinder/gui/presentGui.py
songfinder/gui/screen.py
songfinder/gui/searchGui.py
songfinder/gui/selectionListGui.py
songfinder/gui/simpleProgress.py
songfinder/gui/splash.py
songfinder/gui/themes.py
songfinder/lib/__init__.py
songfinder/data/documentation/README.md
songfinder-1.2.3.dist-info/METADATA
songfinder-1.2.3.dist-info/WHEEL
songfinder-1.2.3.dist-info/entry_points.txt
songfinder-1.2.3.dist-info/RECORD
