Metadata-Version: 2.4
Name: songfinder
Version: 1.2.3
Summary: Slide creation and presentation
Author-email: Danbei <jean_raul@hotmail.fr>
Requires-Python: >=3.7
Requires-Dist: beautifulsoup4
Requires-Dist: cython
Requires-Dist: lxml
Requires-Dist: markdown
Requires-Dist: pillow
Requires-Dist: psutil
Requires-Dist: pypdf2
Requires-Dist: requests
Requires-Dist: setuptools
Provides-Extra: build
Requires-Dist: hatch; extra == 'build'
Provides-Extra: gui
Requires-Dist: psutil; extra == 'gui'
Requires-Dist: screeninfo; (python_version >= '3.6') and extra == 'gui'
Requires-Dist: screeninfo==0.3.1; (python_version <= '3.5') and extra == 'gui'
Provides-Extra: test
Requires-Dist: pylint; extra == 'test'
Requires-Dist: pytest; extra == 'test'
Requires-Dist: pytest-cov; extra == 'test'
Requires-Dist: ruff; (python_version >= '3.7') and extra == 'test'
